gfra/__init__.py
gfra/decorators/__init__.py
gfra/decorators/enabled_cors.py
gfra/endpoint.py
gfra/helpers.py
gfra/utils.py
gfra-0.1.0.dist-info/WHEEL
gfra-0.1.0.dist-info/METADATA
gfra-0.1.0.dist-info/RECORD
